cklogger/__init__.py
cklogger/__main__.py
cklogger-1.0.0.dist-info/LICENSE
cklogger-1.0.0.dist-info/METADATA
cklogger-1.0.0.dist-info/WHEEL
cklogger-1.0.0.dist-info/entry_points.txt
cklogger-1.0.0.dist-info/top_level.txt
cklogger-1.0.0.dist-info/RECORD
