Metadata-Version: 2.1
Name: cklogger
Version: 1.0.0
Summary: Simple pure python utility for sniffing CloudKit usages on iDevices
Home-page: https://github.com/doronz88/cklogger
Author: DoronZ
Project-URL: pymobiledevice3, https://github.com/doronz88/cklogger
Classifier: Programming Language :: Python :: 3.7
Classifier: Programming Language :: Python :: 3.8
Classifier: Programming Language :: Python :: 3.9
Classifier: Programming Language :: Python :: 3.10
License-File: LICENSE
Requires-Dist: click
Requires-Dist: pymobiledevice3 (>=1.29.1)
Requires-Dist: pygments
Requires-Dist: bpylist2
Requires-Dist: coloredlogs
